ufind/__init__.py
util_find-0.1.2.dist-info/licenses/LICENSE
util_find-0.1.2.dist-info/METADATA
util_find-0.1.2.dist-info/WHEEL
util_find-0.1.2.dist-info/top_level.txt
util_find-0.1.2.dist-info/RECORD
