Metadata-Version: 2.4
Name: util-find
Version: 0.1.2
Summary: A utility for finding files and directories
Author-email: birds <cg626@163.com>
Project-URL: git, https://gitee.com/mpypi/util-find
Classifier: Development Status :: 3 - Alpha
Classifier: Intended Audience :: Developers
Classifier: Programming Language :: Python :: 3
Requires-Python: >=3.8
License-File: LICENSE
Dynamic: license-file
